{
  "cache_time": "2025-07-24T00:11:36.287983",
  "keywords": "智能服务机器人分类（商用/家用/医疗等）",
  "max_results": 10,
  "start_date": null,
  "end_date": null,
  "engines": [
    "ddg",
    "sogou",
    "google"
  ],
  "results": [
    {
      "title": "机器人行业分析 一、行业概述定义与分类机器人行业是以人工智 …",
      "url": "https://xueqiu.com/8356201504/322840971",
      "description": "Feb 10, 2025 · 服务机器人：包括家用（扫地机器人）、商用（送餐机器人）、医疗（手术机器人）等。 特种机器人：应用于极端环境（消防、深海探测）或专业场景（农业采摘、安防巡检）。",
      "engine": [
        "ddg"
      ]
    },
    {
      "title": "智能服务机器人，引领行业发展新趋势 - 知乎",
      "url": "https://zhuanlan.zhihu.com/p/663404774",
      "description": "",
      "engine": [
        "ddg"
      ]
    },
    {
      "title": "智能服务机器人 - 全球百科",
      "url": "https://zh.glopedia.org/wiki/智能服务机器人",
      "description": "智能服务机器人以其高效、智能和人性化的特点，正在改变家庭、医疗和商业领域的服务模式。 选择适合的品牌和型号，可显著提升生活和工作效率，同时推动智能化社会的进一步发展。",
      "engine": [
        "ddg"
      ]
    },
    {
      "title": "2025年中国智能服务机器人行业全面解析：分类、政策与未来趋势",
      "url": "https://www.sohu.com/a/876828966_121956424",
      "description": "Mar 28, 2025 · 根据其应用领域的不同，智能服务机器人主要可以分为智能个人或家庭服务机器人和智能专业服务机器人。 本文将详细分析2025年中国智能服务机器人行业的分类、相关政策及未来发展一 …",
      "engine": [
        "ddg"
      ]
    },
    {
      "title": "服务机器人的分类 - 前瞻产业研究院",
      "url": "https://x.qianzhan.com/xcharts/detail/e609ef42fb5ec941.html",
      "description": "Feb 19, 2025 · 在服务机器人分类上，IFR等国际机构按应用领域将服务机器人划分为个人/家用服务机器人和专业服务机器人两类;中国电子学会将服务机器人分为家用服务机器人、公共服务机器人和医疗 …",
      "engine": [
        "ddg"
      ]
    },
    {
      "title": "百家号——从这里影响世界",
      "url": "https://baijiahao.baidu.com/s?id=1749168364064843911",
      "description": "We would like to show you a description here but the site won’t allow us.",
      "engine": [
        "ddg"
      ]
    },
    {
      "title": "商用家用对比_百度百科",
      "url": "https://baike.baidu.com/item/商用家用对比/248252",
      "description": "商用机型追求很高的稳定性，其在同等的条件下适应能力强于家用机。在平均无故障工作时间都超过5000小时以上，有些高的达到20000小时以上；在商业环境安全性也是商用机考虑的问题，多数商 …",
      "engine": [
        "ddg"
      ]
    },
    {
      "title": "海尔家电产品详细参数对比-海尔官网 - Haier",
      "url": "https://www.haier.com/compare.shtml",
      "description": "产品对比 产品对比0/4 高亮不同项 隐藏相同项 清空产品 个人与家用产品 冰箱 冷柜 冰吧 酒柜 洗衣机 空调 电视 热水器 厨房电器 电脑及外设 生活家电 适老家电 商用解决方案 商用空调 商用洗涤 商用显示  …",
      "engine": [
        "ddg"
      ]
    },
    {
      "title": "家用服务机器人三大技术，四大分类 - OFweek智能制造网",
      "url": "https://m.ofweek.com/im/2021-11/ART-201900-8420-30533622.html",
      "description": "Nov 9, 2021 · 专业服务机器人可以分为商用、特种两类，商用服务机器人主要用于零售、餐饮、政务、金融、医院等场景，特种机器人主要用于军用、航空、物流等特殊环境",
      "engine": [
        "ddg"
      ]
    },
    {
      "title": "服务机器人分类包括哪些？ - 机器人自主定位导航方案 | 激光雷 …",
      "url": "https://www.slamtec.com/cn/News/Detail/291",
      "description": "个人（家庭）服务机器人包括扫地机器人、拖地机器人、擦窗机器人、陪伴型机器人、教育机器人及休闲娱乐机器人等，而商用机器人则包括送餐机器人、迎宾机器人、酒店机器人、商场导购机器人、银行 …",
      "engine": [
        "ddg"
      ]
    },
    {
      "title": "2025年中国智能服务机器人行业全面解析：分类、政策与未来趋势_技...",
      "url": "/link?url=hedJjaC291Ok-E9WTygIKqZt6DizBOEjxgzWF-8-ywukdOGxPAMUM8pIJcn0TReQ",
      "description": "2025年3月28日-它们可以应用于家庭场景、商业环境、医疗场所及各类工业单位，在不同的工作情景中发挥着不可或缺的作用。 2.分类情况 根据用途的不同，智能服务机器人...",
      "engine": [
        "sogou"
      ]
    },
    {
      "title": "什么是服务机器人？服务机器人的定义与分类_超绚_声光_装置",
      "url": "/link?url=hedJjaC291Ok-E9WTygIKqZt6DizBOEjWN22EmUW0ROyx9Z4j776DdIynqFpTZFw",
      "description": "2025年2月25日-以及家庭娱乐、病况监视、儿童教育、报时催醒、家用统计等工作。中政商情网 二、医疗机器人医疗机器人主要用于伤病员的手术、救援、转运和康复。...",
      "engine": [
        "sogou"
      ]
    },
    {
      "title": "2025年中国智能服务机器人行业分类及相关政策梳理分析 - 今日头条",
      "url": "/link?url=hedJjaC291PD0T3DYzJqFDoBhFbePHvernilvTOuwmk6ekT1CC3qFfQhSZWkiH5uD-GA4BWiFeo.",
      "description": "2025年3月28日-智能服务机器人，是指在一定环境下为用户提供多种服务的，能够进行主动感知、自主决策执行的机器人产品。智能服务机器人种类繁多，划分标准也不尽...",
      "engine": [
        "sogou"
      ]
    },
    {
      "title": "家用服务机器人三大技术,四大分类|扫地机|人机交互|扫地机器人|人工...",
      "url": "/link?url=hedJjaC291NbWrwHYHKCyPQj_ei8OKC1YrN-rEiLWZnbjDARPtUirtawu2n0c8rU0ztd7q5nl6o.",
      "description": "2021年10月6日-定义：非结构环境，家用、商用根据国际机器人联合会、中国电子学会定义，服务机器人指在 非结构环境 下为人类提供必要服务的多种高技术集成的先进...",
      "engine": [
        "sogou"
      ]
    },
    {
      "title": "人工智能机器人有哪些种类-品牌网-品牌问答-品牌网",
      "url": "/link?url=hedJjaC291Osj6fmiZw1ZsrJjhy2DFHHSq3aTswAtP06HvMExkJlefcbTwBrTaFcB-DEcLerz2Y.",
      "description": "2023年4月10日-人工智能机器人可以根据功能和形态分为很多种类，以下是一些典型的人工智能机器人种类： 1.服务型机器人：主要用于家庭、医院、餐厅等服务场所，能够帮...",
      "engine": [
        "sogou"
      ]
    },
    {
      "title": "服务机器人有哪些-品牌网-品牌问答-品牌网",
      "url": "/link?url=hedJjaC291Osj6fmiZw1ZsrJjhy2DFHHSq3aTswAtP3iKrdRbvnif_cbTwBrTaFcB-DEcLerz2Y.",
      "description": "2023年4月10日-服务机器人的种类和功能将不断丰富和完善。 赞（ 0 ） 举报 醉欲眠卿且去 答服务机器人是指一类能够为人提供各种各样服务的机器人，主要应用于商业、医疗...",
      "engine": [
        "sogou"
      ]
    },
    {
      "title": "机器人分为哪些种类",
      "url": "/link?url=hedJjaC291N6dKD5cUgANF8MIoa0AyspFjjLto6H2mMOw_7L_bPcgCHmfGkNvdZG",
      "description": "2023年8月15日-医疗机器人：用于医疗领域，如手术、诊断、康复等。 5.家用机器人：用于家庭生活，如扫地、洗衣、做饭等。 6. 教育机器人：用于教育领域，如编程机器人...",
      "engine": [
        "sogou"
      ]
    },
    {
      "title": "服务机器人的分类和市场规模-电子发烧友网",
      "url": "/link?url=hedJjaC291Pj9akFfB9kFNjxAcePCkvUNRmj4bgxClIUfScGz-axK7bAp6VRqT6Q",
      "description": "2020年12月26日-商业服务机器人和医疗机器人。服务机器人的主要功能包括导航定位、运动控制和人机交互，涉及的主要技术分别为SLAM（定位和地图创建）、液压控制/电...",
      "engine": [
        "sogou"
      ]
    },
    {
      "title": "智能机器人有哪些种类智能机器人常见类型→十大品牌网",
      "url": "/link?url=hedJjaC291MTxEVZ2I5iVPNOQyCf4CRUnS0dfls39-fTO13urmeXqg..",
      "description": "2023年4月13日-常见的智能机器人类型 1、服务型机器人用于提供各种服务，例如餐饮服务、清洁服务、医疗护理服务、客户服务等。这类机器人通常具有语音识别、人脸...",
      "engine": [
        "sogou"
      ]
    },
    {
      "title": "服务机器人有哪些品类 - 腾讯云开发者社区-腾讯云",
      "url": "/link?url=hedJjaC291NNlyaAPdJIG4sgUN9i2J4jcwMJ03YIpCINwFRBDGlJ8FOfdIcJ0-T5reaVHN88tHY.",
      "description": "2023年7月31日-服务机器人是指具备自主运动、感知环境、实现人机交互等能力的机器人，它可以被应用于不同的场景，如餐饮、医疗、物流等行业。根据其功能和应用场景的...",
      "engine": [
        "sogou"
      ]
    },
    {
      "title": "【服务机器人】行业市场规模：2024年全球服务机器人行业市场规模超过420亿美元公共服务/商用服务机器人占比56%",
      "url": "https://finance.sina.com.cn/roll/2025-03-03/doc-inenkfek6694678.shtml",
      "description": "转自：前瞻产业研究院. 行业主要上市公司：‌诺力股份(603611)、‌海康机器人(HIK ROBOT)、机科股份(835579)等;. 本文核心数据：全球服务机器人行业市场...",
      "date": "2025年3月3日",
      "source": "新浪财经",
      "engine": [
        "google"
      ]
    },
    {
      "title": "机器人革命：下一个工业帝国将由谁定义？",
      "url": "https://m.ofweek.com/ai/2025-05/ART-201717-8120-30663342.html",
      "description": "工业机器人是机器人产业的最大子赛道，占据全球及中国市场主导地位。2021年全球市场中工业机器人占比43%，中国市场占比53%。工业机器人主要用于搬运、...",
      "date": "2025年5月21日",
      "source": "OFweek",
      "engine": [
        "google"
      ]
    },
    {
      "title": "机器人行业的当下与未来——《中国机器人发展年刊》起售",
      "url": "https://www.leaderobot.com/news/5020",
      "description": "哪些区域正在大力推动机器人产业集群发展？哪些细分领域的机器人融资最为迅速？哪些新产品成为焦点？哪些新技术趋势正在出现？哪些企业脱颖而出？",
      "date": "2025年1月6日",
      "source": "leaderobot",
      "engine": [
        "google"
      ]
    },
    {
      "title": "人形机器人发展面临的挑战及未来趋势研判",
      "url": "http://paper.people.com.cn/rmlt/pc/content/202503/03/content_30060620.html",
      "description": "【摘要】人形机器人是人工智能技术与机器人技术深度融合的产物。当前人形机器人已具备相当复杂的运动能力及具有一定的灵活性，在感知和人机互动方面的...",
      "date": "2025年3月3日",
      "source": "人民日报",
      "engine": [
        "google"
      ]
    },
    {
      "title": "【服务机器人】行业市场规模：2024年中国服务机器人行业市场规模超过700亿元 清洁卫生机器人占比超30%",
      "url": "https://www.qianzhan.com/analyst/detail/220/250220-ebf66dfd.html",
      "description": "行业主要上市公司：‌诺力股份(603611)、‌海康机器人(HIK ROBOT)、机科股份(835579)等;. 本文核心数据：中国服务机器人行业市场规模;. 2024年中国服务...",
      "date": "2025年2月20日",
      "source": "前瞻网",
      "engine": [
        "google"
      ]
    },
    {
      "title": "预见2024：《2024年中国服务机器人行业全景图谱》（附市场规模、竞争格局和发展趋势等）",
      "url": "https://finance.sina.com.cn/roll/2024-12-22/doc-ineahxkz0712327.shtml",
      "description": "我国服务机器人行业处于高速发展期。产量波动增长、投资热度高、市场规模扩大。企业分布集中于东部沿海，不同领域竞争企业各有侧重，2029年市场规模有望...",
      "date": "2024年12月22日",
      "source": "新浪财经",
      "engine": [
        "google"
      ]
    },
    {
      "title": "我国服务机器人进入高速增长期",
      "url": "http://www.china-cer.com.cn/guwen/2023010622865.html",
      "description": "近年来，我国服务机器人发展取得哪些成效？苏州大学机电工程学院院长孙立宁表示：按照国际机器人联盟（IFR）的分类，服务机器人一般用于非制造业环境，...",
      "date": "2023年1月6日",
      "source": "经济形势报告网",
      "engine": [
        "google"
      ]
    },
    {
      "title": "半年融资逾75亿，国产机器人熬来好日子",
      "url": "https://m.36kr.com/p/2918668931668610",
      "description": "本周，多达27款人形机器人扎堆亮相世界机器人大会；上半年资本圈也好不热闹，数笔大额融资涌入机器人产业。 据智东西统计，截至2024年6月30日，今年国内...",
      "date": "2024年8月23日",
      "source": "36Kr",
      "engine": [
        "google"
      ]
    },
    {
      "title": "机器人行业价值分析，看这篇就够了",
      "url": "http://www.21jingji.com/article/20210202/herald/bbf88bc37df0a2eb6a9421f541d56f8e.html",
      "description": "第一章行业概况. 据国际标准化组织（ISO）最新资料，将机器人定义为：具有一定程度的自主能力，可在其环境内运动以执行预期任务的可编程执行机构。",
      "date": "2021年2月2日",
      "source": "21财经",
      "engine": [
        "google"
      ]
    },
    {
      "title": "家用服务机器人三大技术，四大分类",
      "url": "https://www.eet-china.com/mp/a81207.html",
      "description": "服务机器人定义：非结构环境，家用、商用根据国际机器人联合会、中国电子学会定义，服务机器人指在非结构环境下为人类提供必要服务的多种高技术集成的...",
      "date": "2021年10月6日",
      "source": "Eet-china",
      "engine": [
        "google"
      ]
    }
  ]
}